zia/.DS_Store
zia/Api/CatalogItemsApi.py
zia/Api/ResultsApi.py
zia/Api/StartApi.py
zia/Api/TasksApi.py
zia/Api/__init__.py
zia/ApiClient.py
zia/__init__.py
zia/utils/ziaretry.py
zia_sdk-0.1.9.dist-info/METADATA
zia_sdk-0.1.9.dist-info/WHEEL
zia_sdk-0.1.9.dist-info/RECORD
