Metadata-Version: 2.3
Name: zia-sdk
Version: 0.1.9
Summary: 
Author: Toby Thomas
Author-email: toby@thomas.red
Requires-Python: >=3.10
Classifier: Programming Language :: Python :: 3
Classifier: Programming Language :: Python :: 3.10
Classifier: Programming Language :: Python :: 3.11
Classifier: Programming Language :: Python :: 3.12
Classifier: Programming Language :: Python :: 3.13
Requires-Dist: asyncio (>=3.4.3,<4.0.0)
Requires-Dist: requests (>=2.32.4,<3.0.0)
